rk_digi-0.1.0.dist-info/licenses/LICENSE
rkdigi/__init__.py
rk_digi-0.1.0.dist-info/METADATA
rk_digi-0.1.0.dist-info/WHEEL
rk_digi-0.1.0.dist-info/top_level.txt
rk_digi-0.1.0.dist-info/RECORD
