Metadata-Version: 2.4
Name: rk-digi
Version: 0.1.0
Summary: Python package with useful stuff for projects in Randers kommune digitalisering
Author: Randers Kommune Digitalisering
License-Expression: MIT
Requires-Python: >=3.7
License-File: LICENSE
Dynamic: license-file
